ipranger/__init__.py
ipranger/ipranger.py
ipranger-1.1.2.dist-info/LICENSE
ipranger-1.1.2.dist-info/METADATA
ipranger-1.1.2.dist-info/WHEEL
ipranger-1.1.2.dist-info/entry_points.txt
ipranger-1.1.2.dist-info/top_level.txt
ipranger-1.1.2.dist-info/RECORD
