Metadata-Version: 2.1
Name: ipranger
Version: 1.1.2
Summary: A python package and commandline tool for generating IPv4-addresses based on a schema.
Home-page: https://github.com/bytebutcher/ipranger
Author: bytebutcher
Author-email: thomas.engel.web@gmail.com
License: GPL-3.0
Platform: UNKNOWN
Classifier: Programming Language :: Python :: 3
Classifier: Operating System :: OS Independent
License-File: LICENSE
Requires-Dist: dacite (==1.6.0)
Requires-Dist: parameterized (==0.8.1)
Requires-Dist: pyparsing (==3.0.6)
